s1280247_lean2/__init__.py
s1280247_lean2/statistics/__init__.py
s1280247_lean2/statistics/frequenciesOfItems.py
s1280247_lean2/visualization/__init__.py
s1280247_lean2/visualization/heatMapItemsFrequencies.py
s1280247_learn2-2023.7.27.dist-info/METADATA
s1280247_learn2-2023.7.27.dist-info/WHEEL
s1280247_learn2-2023.7.27.dist-info/top_level.txt
s1280247_learn2-2023.7.27.dist-info/RECORD
